icinga-tray/__init__.py
icinga-tray/icinga_fetcher.py
icinga-tray/icinga_tray.py
icinga-tray/img/icinga_crit.png
icinga-tray/img/icinga_off.png
icinga-tray/img/icinga_ok.png
icinga-tray/img/icinga_unknown.png
icinga-tray/img/icinga_warn.png
icinga-tray/img/notification_crit.ico
icinga-tray/img/notification_crit.png
icinga-tray/img/notification_ok.ico
icinga-tray/img/notification_ok.png
icinga-tray/img/notification_unknown.ico
icinga-tray/img/notification_unknown.png
icinga-tray/img/notification_unkown.png
icinga-tray/img/notification_warn.ico
icinga-tray/img/notification_warn.png
icinga_tray/__init__.py
icinga_tray/icinga_fetcher.py
icinga_tray/icinga_tray.py
icinga_tray/icinga_tray_gtk.py
icinga_tray/img/icinga_crit.png
icinga_tray/img/icinga_off.png
icinga_tray/img/icinga_ok.png
icinga_tray/img/icinga_unknown.png
icinga_tray/img/icinga_warn.png
icinga_tray/img/notification_crit.ico
icinga_tray/img/notification_crit.png
icinga_tray/img/notification_ok.ico
icinga_tray/img/notification_ok.png
icinga_tray/img/notification_unknown.ico
icinga_tray/img/notification_unknown.png
icinga_tray/img/notification_unkown.png
icinga_tray/img/notification_warn.ico
icinga_tray/img/notification_warn.png
icinga_tray-0.1.5.dist-info/METADATA
icinga_tray-0.1.5.dist-info/WHEEL
icinga_tray-0.1.5.dist-info/entry_points.txt
icinga_tray-0.1.5.dist-info/top_level.txt
icinga_tray-0.1.5.dist-info/RECORD
