Metadata-Version: 2.1
Name: icinga-tray
Version: 0.1.5
Summary: A small script to display a tray icon with icinga information
Author: Johannes Battenberg
Author-email: joe@chaoticneutral.eu
Keywords: icinga,tray,icon,monitoring,icingaweb,icinga2
Classifier: License :: OSI Approved :: BSD License
Classifier: Programming Language :: Python :: 3
Classifier: Operating System :: OS Independent
Requires-Python: >=3.8
Requires-Dist: PyQt6
Requires-Dist: plyer
Requires-Dist: requests
Requires-Dist: keyring
Requires-Dist: appdirs
